LICENSE
MANIFEST.in
README.rst
django-admin-hbs.py
djangohbs.py
requirements.txt
setup.py
test.py
django_hbs_makemessages.egg-info/PKG-INFO
django_hbs_makemessages.egg-info/SOURCES.txt
django_hbs_makemessages.egg-info/dependency_links.txt
django_hbs_makemessages.egg-info/requires.txt
django_hbs_makemessages.egg-info/top_level.txt