Metadata-Version: 1.1
Name: django-hbs-makemessages
Version: 0.9.6
Summary: Library providing makemessages for Handlebars.js templates
Home-page: https://github.com/rafalp/django-hbs-makemessages
Author: Rafał Pitoń
Author-email: kontakt@rpiton.com
License: MIT
Platform: UNKNOWN
Classifier: Development Status :: 5 - Production/Stable
Classifier: Environment :: Console
Classifier: Framework :: Django
Classifier: Intended Audience :: Developers
Classifier: License :: OSI Approved :: MIT License
Classifier: Operating System :: OS Independent
Classifier: Programming Language :: Python
Classifier: Programming Language :: Python :: 2.7
Classifier: Programming Language :: Python :: 3.2
Classifier: Programming Language :: Python :: 3.3
Classifier: Programming Language :: Python :: 3.4
Classifier: Topic :: Software Development :: Libraries :: Python Modules
